flexagg/__init__.py
flexagg/config.py
flexagg/loader.py
flexagg/main.py
flexagg/models.py
flexagg/register.py
flexagg/utils/__init__.py
flexagg/utils/echo.py
flexagg/utils/panic.py
flexagg/utils/secrets.py
flexagg-builtin-apps/secrets.py
flexagg-builtin-apps/config/path.py
flexagg-builtin-apps/config/secrets.py
flexagg-0.1.1.dist-info/METADATA
flexagg-0.1.1.dist-info/WHEEL
flexagg-0.1.1.dist-info/entry_points.txt
flexagg-0.1.1.dist-info/RECORD
